{"internal":{"uuid":{"value":"32852112-246a-4ad4-bf17-6f02100aaa22"},"ext":{},"units_info":null},"data":{"validation_descriptor_file":"system_data_validation_descriptors.json","version_info":{"julia_version":"1.5.2","package_info":"Status `~/work/PowerSystems.jl/PowerSystems.jl/docs/Manifest.toml`\n  [ae81ac8f] ASL_jll v0.1.1+3\n  [4fba245c] ArrayInterface v2.13.7\n  [56f22d72] Artifacts v1.3.0\n  [6e4b80f9] BenchmarkTools v0.5.0\n  [b99e7846] BinaryProvider v0.5.10\n  [a74b3585] Blosc v0.7.0\n  [0b7ba130] Blosc_jll v1.14.3+1\n  [6e34b625] Bzip2_jll v1.0.6+5\n  [336ed68f] CSV v0.7.7\n  [49dc2e85] Calculus v0.5.1\n  [324d7699] CategoricalArrays v0.8.3\n  [523fee87] CodecBzip2 v0.7.2\n  [944b1d66] CodecZlib v0.7.0\n  [bbf7d656] CommonSubexpressions v0.3.0\n  [34da2185] Compat v3.23.0\n  [e66e0078] CompilerSupportLibraries_jll v0.3.4+0\n  [a8cc5b0e] Crayons v4.0.4\n  [9a962f9c] DataAPI v1.3.0\n  [a93c6f00] DataFrames v0.21.8\n  [864edb3b] DataStructures v0.18.8\n  [e2d170a0] DataValueInterfaces v1.0.0\n  [163ba53b] DiffResults v1.0.2\n  [b552c78f] DiffRules v1.0.1\n  [b4f34e82] Distances v0.9.2\n  [ffbed154] DocStringExtensions v0.8.3\n  [e30172f5] Documenter v0.25.2\n  [6a86dc24] FiniteDiff v2.7.0\n  [59287772] Formatting v0.4.1\n  [f6369f11] ForwardDiff v0.10.12\n  [f67ccb44] HDF5 v0.13.6\n  [0234f1f7] HDF5_jll v1.10.5+7\n  [cd3eb016] HTTP v0.8.19\n  [2cd47ed4] InfrastructureSystems v1.0.0\n  [83e8ac13] IniFile v0.5.0\n  [41ab1584] InvertedIndices v1.0.0\n  [b6b21f68] Ipopt v0.6.3\n  [9cc047cb] Ipopt_jll v3.13.2+0\n  [82899510] IteratorInterfaceExtensions v1.0.0\n  [692b3bcd] JLLWrappers v1.1.3\n  [682c06a0] JSON v0.21.1\n  [0f8b85d8] JSON3 v1.4.0\n  [7d188eb4] JSONSchema v0.3.2\n  [4076af6c] JuMP v0.21.5\n  [d3d80556] LineSearches v7.1.0\n  [98b081ad] Literate v2.7.0\n  [5ced341a] Lz4_jll v1.9.2+2\n  [d00139f3] METIS_jll v5.1.0+4\n  [d7ed1dd3] MUMPS_seq_jll v5.2.1+3\n  [1914dd2f] MacroTools v0.5.6\n  [b8f27783] MathOptInterface v0.9.17\n  [fdba3010] MathProgBase v0.7.8\n  [739be429] MbedTLS v1.0.3\n  [c8ffd9c3] MbedTLS_jll v2.16.8+0\n  [e1d29d7a] Missings v0.4.4\n  [ffc61752] Mustache v1.0.8\n  [d8a4904e] MutableArithmetics v0.2.10\n  [d41bc354] NLSolversBase v7.7.1\n  [2774e3e8] NLsolve v4.4.1\n  [77ba4419] NaNMath v0.3.4\n  [656ef2d0] OpenBLAS32_jll v0.3.10+0\n  [efe28fd5] OpenSpecFun_jll v0.5.3+4\n  [bac558e1] OrderedCollections v1.3.1\n  [d96e819e] Parameters v0.12.1\n  [69de0a69] Parsers v1.0.11\n  [2dfb63ee] PooledArrays v0.5.3\n  [bcd98974] PowerSystems v1.0.0 `~/work/PowerSystems.jl/PowerSystems.jl`\n  [08abe8d2] PrettyTables v0.9.1\n  [3cdcf5f2] RecipesBase v1.1.0\n  [189a3867] Reexport v0.2.0\n  [ae029012] Requires v1.1.0\n  [91c51154] SentinelArrays v1.2.16\n  [a2af1166] SortingAlgorithms v0.3.1\n  [276daf66] SpecialFunctions v0.10.3\n  [90137ffa] StaticArrays v0.12.4\n  [856f2bd8] StructTypes v1.1.0\n  [3783bdb8] TableTraits v1.0.0\n  [bd369af6] Tables v1.1.0\n  [9e3dc215] TimeSeries v0.19.1\n  [3bb67fe8] TranscodingStreams v0.9.5\n  [3a884ed6] UnPack v1.0.2\n  [ddb6d928] YAML v0.4.2\n  [a5390f91] ZipFile v0.9.3\n  [83775a58] Zlib_jll v1.2.11+18\n  [3161d3a3] Zstd_jll v1.4.5+2\n  [2a0f44e3] Base64\n  [ade2ca70] Dates\n  [8bb1440f] DelimitedFiles\n  [8ba89e20] Distributed\n  [9fa8497b] Future\n  [b77e0a4c] InteractiveUtils\n  [76f85450] LibGit2\n  [8f399da3] Libdl\n  [37e2e46d] LinearAlgebra\n  [56ddb016] Logging\n  [d6f4376e] Markdown\n  [a63ad114] Mmap\n  [44cfe95a] Pkg\n  [de0858da] Printf\n  [3fa0cd96] REPL\n  [9a3f8284] Random\n  [ea8e919c] SHA\n  [9e88b42a] Serialization\n  [1a1011a3] SharedArrays\n  [6462fe0b] Sockets\n  [2f01184e] SparseArrays\n  [10745b16] Statistics\n  [8dfed614] Test\n  [cf7118a7] UUIDs\n  [4ec0a83e] Unicode\n"},"internal":{"uuid":{"value":"17683789-ca9e-4873-9082-0d2256cd2eb7"},"ext":{},"units_info":null},"components":[{"number":1,"base_voltage":230.0,"bustype":"PV","angle":0.048935017968641414,"name":"bus1","magnitude":1.0,"__metadata__":{"module":"PowerSystems","type":"Bus"},"internal":{"uuid":{"value":"c24ec8bd-5193-44b7-ad12-1a564e89b548"},"ext":null,"units_info":null},"area":{"value":"a3dab925-0eaf-41b8-8dc6-9d0c503f7f44"},"ext":{},"voltage_limits":{"min":0.9,"max":1.1},"load_zone":{"value":"4b80d1a8-eb08-4da5-a53a-a2bb68140127"}},{"number":4,"base_voltage":230.0,"bustype":"REF","angle":0.0,"name":"bus4","magnitude":1.0,"__metadata__":{"module":"PowerSystems","type":"Bus"},"internal":{"uuid":{"value":"90108306-d127-449d-b05f-51028c096e01"},"ext":null,"units_info":null},"area":{"value":"a3dab925-0eaf-41b8-8dc6-9d0c503f7f44"},"ext":{},"voltage_limits":{"min":0.9,"max":1.1},"load_zone":{"value":"4b80d1a8-eb08-4da5-a53a-a2bb68140127"}},{"number":10,"base_voltage":230.0,"bustype":"PV","angle":0.06266307973312801,"name":"bus5","magnitude":1.0,"__metadata__":{"module":"PowerSystems","type":"Bus"},"internal":{"uuid":{"value":"88e9f342-682c-4771-b251-c10619712f6c"},"ext":null,"units_info":null},"area":{"value":"a3dab925-0eaf-41b8-8dc6-9d0c503f7f44"},"ext":{},"voltage_limits":{"min":0.9,"max":1.1},"load_zone":{"value":"4b80d1a8-eb08-4da5-a53a-a2bb68140127"}},{"number":2,"base_voltage":230.0,"bustype":"PQ","angle":-0.012822061349776342,"name":"bus2","magnitude":1.08407,"__metadata__":{"module":"PowerSystems","type":"Bus"},"internal":{"uuid":{"value":"0344abe8-0017-4429-a848-802e83513cce"},"ext":null,"units_info":null},"area":{"value":"a3dab925-0eaf-41b8-8dc6-9d0c503f7f44"},"ext":{},"voltage_limits":{"min":0.9,"max":1.1},"load_zone":{"value":"4b80d1a8-eb08-4da5-a53a-a2bb68140127"}},{"number":3,"base_voltage":230.0,"bustype":"PV","angle":-0.00976895688926266,"name":"bus3","magnitude":1.0,"__metadata__":{"module":"PowerSystems","type":"Bus"},"internal":{"uuid":{"value":"8c48cc65-65b9-48b6-a6c4-f6400b77ffc0"},"ext":null,"units_info":null},"area":{"value":"a3dab925-0eaf-41b8-8dc6-9d0c503f7f44"},"ext":{},"voltage_limits":{"min":0.9,"max":1.1},"load_zone":{"value":"4b80d1a8-eb08-4da5-a53a-a2bb68140127"}},{"load_response":0.0,"name":"1","__metadata__":{"module":"PowerSystems","type":"Area"},"internal":{"uuid":{"value":"a3dab925-0eaf-41b8-8dc6-9d0c503f7f44"},"ext":null,"units_info":null},"peak_active_power":0.0,"peak_reactive_power":0.0,"time_series_container":[]},{"services":[],"x":0.0108,"b":{"from":0.00926,"to":0.00926},"r":0.00108,"rate":12.0,"available":true,"time_series_container":[],"name":"4","reactive_power_flow":0.0,"arc":{"value":"85e79ec1-ecfa-4fb9-a634-e7ca19cca2e2"},"__metadata__":{"module":"PowerSystems","type":"Line"},"internal":{"uuid":{"value":"f4555818-e86c-49af-a250-2c8003939e74"},"ext":null,"units_info":null},"ext":{},"active_power_flow":0.0,"angle_limits":{"min":-0.5235987755982988,"max":0.5235987755982988}},{"services":[],"x":0.0281,"b":{"from":0.00356,"to":0.00356},"r":0.00281,"rate":2.0,"available":true,"time_series_container":[],"name":"1","reactive_power_flow":0.0,"arc":{"value":"f45b1f74-7e52-499a-927a-1bb0a120b207"},"__metadata__":{"module":"PowerSystems","type":"Line"},"internal":{"uuid":{"value":"494ad28e-79f4-42e8-9ca5-3a067eb10e08"},"ext":null,"units_info":null},"ext":{},"active_power_flow":0.0,"angle_limits":{"min":-0.5235987755982988,"max":0.5235987755982988}},{"services":[],"x":0.0304,"b":{"from":0.00329,"to":0.00329},"r":0.00304,"rate":2.0,"available":true,"time_series_container":[],"name":"2","reactive_power_flow":0.0,"arc":{"value":"9aced8db-38a3-444e-a305-7470a0e3598f"},"__metadata__":{"module":"PowerSystems","type":"Line"},"internal":{"uuid":{"value":"ec80c293-4b8f-43b0-8c06-7c595adce9b0"},"ext":null,"units_info":null},"ext":{},"active_power_flow":0.0,"angle_limits":{"min":-0.5235987755982988,"max":0.5235987755982988}},{"services":[],"x":0.0297,"b":{"from":0.00337,"to":0.00337},"r":0.00297,"rate":2.0,"available":true,"time_series_container":[],"name":"7","reactive_power_flow":0.0,"arc":{"value":"d766bb2b-d079-4030-a64a-f9494f238b53"},"__metadata__":{"module":"PowerSystems","type":"Line"},"internal":{"uuid":{"value":"23713682-ed88-43d1-9684-6888d41051f3"},"ext":null,"units_info":null},"ext":{},"active_power_flow":0.0,"angle_limits":{"min":-0.5235987755982988,"max":0.5235987755982988}},{"services":[],"x":0.0064,"b":{"from":0.01563,"to":0.01563},"r":0.00064,"rate":10.0,"available":true,"time_series_container":[],"name":"3","reactive_power_flow":0.0,"arc":{"value":"acd2a851-c68a-43d8-8f53-1da7ddcdd88f"},"__metadata__":{"module":"PowerSystems","type":"Line"},"internal":{"uuid":{"value":"d326a5a4-7494-4f6a-8100-21b38a0701a3"},"ext":null,"units_info":null},"ext":{},"active_power_flow":0.0,"angle_limits":{"min":-0.5235987755982988,"max":0.5235987755982988}},{"base_power":100.0,"rating":0.6,"services":[],"bus":{"value":"8c48cc65-65b9-48b6-a6c4-f6400b77ffc0"},"available":true,"time_series_container":[{"length":24,"name":"max_active_power","initial_timestamp":"2020-10-27T00:00:00.0","resolution":{"value":3600000,"type":"Millisecond"},"internal":{"uuid":{"value":"e22ddece-6a3c-459a-a33c-fc50642406ad"},"ext":null,"units_info":null},"time_series_uuid":{"value":"66012eec-74cb-4766-9011-34c60f612f98"},"scaling_factor_multiplier":{"__metadata__":{"function":"get_max_active_power","module":"PowerSystems"}},"__metadata__":{"module":"InfrastructureSystems","type":"SingleTimeSeriesMetadata"}}],"name":"SolarBusC","power_factor":1.0,"active_power":0.0,"dynamic_injector":null,"__metadata__":{"module":"PowerSystems","type":"RenewableDispatch"},"internal":{"uuid":{"value":"d0bfff7c-1ee2-4a75-b51b-93e31e88b0c5"},"ext":null,"units_info":null},"reactive_power_limits":{"min":0.0,"max":0.0},"ext":{},"operation_cost":{"fixed":0.0,"variable":{"cost":0.0},"__metadata__":{"module":"PowerSystems","type":"TwoPartCost"}},"reactive_power":0.0,"prime_mover":"PVe"},{"base_power":100.0,"rating":0.6,"services":[],"bus":{"value":"88e9f342-682c-4771-b251-c10619712f6c"},"available":true,"time_series_container":[{"length":24,"name":"max_active_power","initial_timestamp":"2020-10-27T00:00:00.0","resolution":{"value":3600000,"type":"Millisecond"},"internal":{"uuid":{"value":"bce31cf5-2f02-4d97-815f-be59e71021cb"},"ext":null,"units_info":null},"time_series_uuid":{"value":"bb644a1f-5a0e-442b-9356-5bedba85d24b"},"scaling_factor_multiplier":{"__metadata__":{"function":"get_max_active_power","module":"PowerSystems"}},"__metadata__":{"module":"InfrastructureSystems","type":"SingleTimeSeriesMetadata"}}],"name":"WindBusA","power_factor":1.0,"active_power":0.0,"dynamic_injector":null,"__metadata__":{"module":"PowerSystems","type":"RenewableDispatch"},"internal":{"uuid":{"value":"6614008b-c22b-40e3-88a9-bca187d1b663"},"ext":null,"units_info":null},"reactive_power_limits":{"min":0.0,"max":0.0},"ext":{},"operation_cost":{"fixed":0.0,"variable":{"cost":0.0},"__metadata__":{"module":"PowerSystems","type":"TwoPartCost"}},"reactive_power":0.0,"prime_mover":"WT"},{"internal":{"uuid":{"value":"85e79ec1-ecfa-4fb9-a634-e7ca19cca2e2"},"ext":null,"units_info":null},"to":{"value":"8c48cc65-65b9-48b6-a6c4-f6400b77ffc0"},"from":{"value":"0344abe8-0017-4429-a848-802e83513cce"},"__metadata__":{"module":"PowerSystems","type":"Arc"}},{"internal":{"uuid":{"value":"acd2a851-c68a-43d8-8f53-1da7ddcdd88f"},"ext":null,"units_info":null},"to":{"value":"88e9f342-682c-4771-b251-c10619712f6c"},"from":{"value":"c24ec8bd-5193-44b7-ad12-1a564e89b548"},"__metadata__":{"module":"PowerSystems","type":"Arc"}},{"internal":{"uuid":{"value":"9aced8db-38a3-444e-a305-7470a0e3598f"},"ext":null,"units_info":null},"to":{"value":"90108306-d127-449d-b05f-51028c096e01"},"from":{"value":"c24ec8bd-5193-44b7-ad12-1a564e89b548"},"__metadata__":{"module":"PowerSystems","type":"Arc"}},{"internal":{"uuid":{"value":"f45b1f74-7e52-499a-927a-1bb0a120b207"},"ext":null,"units_info":null},"to":{"value":"0344abe8-0017-4429-a848-802e83513cce"},"from":{"value":"c24ec8bd-5193-44b7-ad12-1a564e89b548"},"__metadata__":{"module":"PowerSystems","type":"Arc"}},{"internal":{"uuid":{"value":"3bccc1ec-494f-4471-9548-7048e6820b2c"},"ext":null,"units_info":null},"to":{"value":"90108306-d127-449d-b05f-51028c096e01"},"from":{"value":"8c48cc65-65b9-48b6-a6c4-f6400b77ffc0"},"__metadata__":{"module":"PowerSystems","type":"Arc"}},{"internal":{"uuid":{"value":"d766bb2b-d079-4030-a64a-f9494f238b53"},"ext":null,"units_info":null},"to":{"value":"88e9f342-682c-4771-b251-c10619712f6c"},"from":{"value":"90108306-d127-449d-b05f-51028c096e01"},"__metadata__":{"module":"PowerSystems","type":"Arc"}},{"services":[],"rate":10.0,"x":0.0297,"r":0.00297,"available":true,"time_series_container":[],"name":"5","reactive_power_flow":0.0,"arc":{"value":"3bccc1ec-494f-4471-9548-7048e6820b2c"},"__metadata__":{"module":"PowerSystems","type":"PhaseShiftingTransformer"},"internal":{"uuid":{"value":"e98d9c43-60c3-46bc-bf38-dc801d28cf11"},"ext":null,"units_info":null},"ext":{},"α":0.017453292519943295,"primary_shunt":0.00337,"active_power_flow":0.0,"tap":1.05},{"services":[],"rate":4.26,"x":0.03274425,"r":0.003274425,"available":true,"time_series_container":[],"name":"6","reactive_power_flow":0.0,"arc":{"value":"3bccc1ec-494f-4471-9548-7048e6820b2c"},"__metadata__":{"module":"PowerSystems","type":"PhaseShiftingTransformer"},"internal":{"uuid":{"value":"f6b5301b-a0d7-4524-a708-3c4ae4799e87"},"ext":null,"units_info":null},"ext":{},"α":0.017453292519943295,"primary_shunt":0.003056689342403628,"active_power_flow":0.0,"tap":0.9523809523809523},{"__metadata__":{"module":"PowerSystems","type":"LoadZone"},"name":"1","internal":{"uuid":{"value":"4b80d1a8-eb08-4da5-a53a-a2bb68140127"},"ext":null,"units_info":null},"peak_active_power":10.0,"peak_reactive_power":3.2869,"time_series_container":[]},{"base_power":100.0,"rating":6.5,"services":[],"bus":{"value":"8c48cc65-65b9-48b6-a6c4-f6400b77ffc0"},"available":true,"time_series_container":[],"name":"Solitude","status":true,"active_power":3.24498,"dynamic_injector":null,"__metadata__":{"module":"PowerSystems","type":"ThermalStandard"},"fuel":"NUCLEAR","internal":{"uuid":{"value":"0fac8433-3c54-498c-86c6-ee3d73acf1e4"},"ext":null,"units_info":null},"reactive_power_limits":{"min":-3.9,"max":3.9},"ext":{},"operation_cost":{"start_up":0.0,"fixed":0.0,"shut_down":0.0,"variable":{"cost":[0.0,3000.0]},"__metadata__":{"module":"PowerSystems","type":"ThreePartCost"}},"time_limits":null,"ramp_limits":{"up":0.0,"down":0.0},"time_at_status":1.0e6,"active_power_limits":{"min":0.0,"max":5.2},"reactive_power":3.9,"prime_mover":"ST"},{"base_power":100.0,"rating":2.125,"services":[],"bus":{"value":"c24ec8bd-5193-44b7-ad12-1a564e89b548"},"available":true,"time_series_container":[],"name":"Park City","status":true,"active_power":1.7,"dynamic_injector":null,"__metadata__":{"module":"PowerSystems","type":"ThermalStandard"},"fuel":"NATURAL_GAS","internal":{"uuid":{"value":"11636396-3237-469a-9fc4-b825f1c87cdf"},"ext":null,"units_info":null},"reactive_power_limits":{"min":-1.275,"max":1.275},"ext":{},"operation_cost":{"start_up":0.0,"fixed":0.0,"shut_down":0.0,"variable":{"cost":[0.0,1500.0]},"__metadata__":{"module":"PowerSystems","type":"ThreePartCost"}},"time_limits":null,"ramp_limits":{"up":0.0,"down":0.0},"time_at_status":1.0e6,"active_power_limits":{"min":0.0,"max":1.7},"reactive_power":1.275,"prime_mover":"CC"},{"base_power":100.0,"rating":0.5,"services":[],"bus":{"value":"c24ec8bd-5193-44b7-ad12-1a564e89b548"},"available":true,"time_series_container":[],"name":"Alta","status":true,"active_power":0.4,"dynamic_injector":null,"__metadata__":{"module":"PowerSystems","type":"ThermalStandard"},"fuel":"NATURAL_GAS","internal":{"uuid":{"value":"6cbacc6b-3b67-407b-9709-0241298e593f"},"ext":null,"units_info":null},"reactive_power_limits":{"min":-0.3,"max":0.3},"ext":{},"operation_cost":{"start_up":0.0,"fixed":0.0,"shut_down":0.0,"variable":{"cost":[0.0,1400.0]},"__metadata__":{"module":"PowerSystems","type":"ThreePartCost"}},"time_limits":null,"ramp_limits":{"up":0.0,"down":0.0},"time_at_status":1.0e6,"active_power_limits":{"min":0.0,"max":0.4},"reactive_power":0.3,"prime_mover":"CT"},{"base_power":100.0,"rating":7.5,"services":[],"bus":{"value":"88e9f342-682c-4771-b251-c10619712f6c"},"available":true,"time_series_container":[],"name":"Brighton","status":true,"active_power":4.70694,"dynamic_injector":null,"__metadata__":{"module":"PowerSystems","type":"ThermalStandard"},"fuel":"COAL","internal":{"uuid":{"value":"906ec963-bcd4-4672-87cd-a3b3da5d6958"},"ext":null,"units_info":null},"reactive_power_limits":{"min":-4.5,"max":4.5},"ext":{},"operation_cost":{"start_up":0.0,"fixed":0.0,"shut_down":0.0,"variable":{"cost":[0.0,1000.0]},"__metadata__":{"module":"PowerSystems","type":"ThreePartCost"}},"time_limits":null,"ramp_limits":{"up":0.0,"down":0.0},"time_at_status":1.0e6,"active_power_limits":{"min":0.0,"max":6.0},"reactive_power":-1.6503899999999998,"prime_mover":"ST"},{"base_power":100.0,"rating":2.5,"services":[],"bus":{"value":"90108306-d127-449d-b05f-51028c096e01"},"available":true,"time_series_container":[],"name":"Sundance","status":true,"active_power":0.0,"dynamic_injector":null,"__metadata__":{"module":"PowerSystems","type":"ThermalStandard"},"fuel":"NATURAL_GAS","internal":{"uuid":{"value":"49ce496a-f0d1-4e59-901b-0d270be3c815"},"ext":null,"units_info":null},"reactive_power_limits":{"min":-1.5,"max":1.5},"ext":{},"operation_cost":{"start_up":0.0,"fixed":0.0,"shut_down":0.0,"variable":{"cost":[0.0,4000.0]},"__metadata__":{"module":"PowerSystems","type":"ThreePartCost"}},"time_limits":null,"ramp_limits":{"up":0.0,"down":0.0},"time_at_status":1.0e6,"active_power_limits":{"min":0.0,"max":2.0},"reactive_power":-0.10801999999999999,"prime_mover":"CC"},{"base_power":100.0,"services":[],"model":"ConstantPower","bus":{"value":"90108306-d127-449d-b05f-51028c096e01"},"available":true,"time_series_container":[{"length":24,"name":"max_active_power","initial_timestamp":"2020-10-27T00:00:00.0","resolution":{"value":3600000,"type":"Millisecond"},"internal":{"uuid":{"value":"19af32da-f0fa-4367-bc0d-75fd7c23e520"},"ext":null,"units_info":null},"time_series_uuid":{"value":"a327fc65-047a-495e-a228-46ac035e50e6"},"scaling_factor_multiplier":{"__metadata__":{"function":"get_max_active_power","module":"PowerSystems"}},"__metadata__":{"module":"InfrastructureSystems","type":"SingleTimeSeriesMetadata"}}],"name":"bus4","active_power":4.0,"dynamic_injector":null,"__metadata__":{"module":"PowerSystems","type":"PowerLoad"},"max_active_power":4.0,"internal":{"uuid":{"value":"3e05ebf1-ce5f-4506-9486-25d04a96d65c"},"ext":null,"units_info":null},"max_reactive_power":1.3147,"ext":{},"reactive_power":1.3147},{"base_power":100.0,"services":[],"model":"ConstantPower","bus":{"value":"0344abe8-0017-4429-a848-802e83513cce"},"available":true,"time_series_container":[{"length":24,"name":"max_active_power","initial_timestamp":"2020-10-27T00:00:00.0","resolution":{"value":3600000,"type":"Millisecond"},"internal":{"uuid":{"value":"d9ace840-24fd-488a-b345-2a84c045f14f"},"ext":null,"units_info":null},"time_series_uuid":{"value":"55540450-88b4-411d-a4e3-4577d2cb0f70"},"scaling_factor_multiplier":{"__metadata__":{"function":"get_max_active_power","module":"PowerSystems"}},"__metadata__":{"module":"InfrastructureSystems","type":"SingleTimeSeriesMetadata"}}],"name":"bus2","active_power":3.0,"dynamic_injector":null,"__metadata__":{"module":"PowerSystems","type":"PowerLoad"},"max_active_power":3.0,"internal":{"uuid":{"value":"c9c71a8e-fac9-45a6-bdc7-15ad8f5e2e38"},"ext":null,"units_info":null},"max_reactive_power":0.9861,"ext":{},"reactive_power":0.9861},{"base_power":100.0,"services":[],"model":"ConstantPower","bus":{"value":"8c48cc65-65b9-48b6-a6c4-f6400b77ffc0"},"available":true,"time_series_container":[{"length":24,"name":"max_active_power","initial_timestamp":"2020-10-27T00:00:00.0","resolution":{"value":3600000,"type":"Millisecond"},"internal":{"uuid":{"value":"291687ba-ed78-40fd-9bc7-214a970e7592"},"ext":null,"units_info":null},"time_series_uuid":{"value":"fb3b1e61-888d-4ba8-b6d2-4b9ae1473e84"},"scaling_factor_multiplier":{"__metadata__":{"function":"get_max_active_power","module":"PowerSystems"}},"__metadata__":{"module":"InfrastructureSystems","type":"SingleTimeSeriesMetadata"}}],"name":"bus3","active_power":3.0,"dynamic_injector":null,"__metadata__":{"module":"PowerSystems","type":"PowerLoad"},"max_active_power":3.0,"internal":{"uuid":{"value":"bacf942a-4b99-4c77-bd68-871c2abed409"},"ext":null,"units_info":null},"max_reactive_power":0.9861,"ext":{},"reactive_power":0.9861}],"time_series_storage_file":"system_data_time_series_storage.h5","time_series_storage_type":"InfrastructureSystems.Hdf5TimeSeriesStorage","time_series_params":{"__metadata__":{"module":"InfrastructureSystems","type":"TimeSeriesParameters"},"resolution":{"value":3600000,"type":"Millisecond"},"forecast_params":{"initial_timestamp":"0001-01-01T00:00:00.0","interval":{"value":0,"type":"Minute"},"horizon":0,"count":0,"__metadata__":{"module":"InfrastructureSystems","type":"ForecastParameters"}}}},"units_settings":{"base_value":100.0,"unit_system":"SYSTEM_BASE"},"frequency":60.0,"runchecks":true,"data_format_version":"1.0.0"}